{
  "IsEncrypted": false,
  "Values": {
    "AzureWebJobsStorage": "",
    "FUNCTIONS_WORKER_RUNTIME": "dotnet-isolated",
    "WORKSPACE_NAME": "synapse-mgdc-us",
    "PIPELINE_NAME": "Oversharing_LowCode",
    "STORAGE_CONTAINER_NAME": "oversharing-lowcode",
    "STORAGE_ACCOUNT_NAME": "agmgdcstorage",
    "DELTA_DAYS": "7",
    "TURN_ON_ADX": "true",
    "ADX_CLUSTER_NAME": "mgdc-us",
    "ADX_RESOURCE_GROUP_NAME": "mgdc-us-rg",
    "ADX_SUBSCRIPTION_ID" : "cb422ab7-e1e5-47d3-a4c1-4c192f132d3f"
  }
}